scsims/__init__.py
scsims/data.py
scsims/inference.py
scsims/lightning_train.py
scsims/model.py
scsims/networking.py
scsims/pretraining.py
scsims/scvi_api.py
scsims/temperature_scaling.py
scsims/tests.py
scsims-3.0.6.dist-info/LICENSE
scsims-3.0.6.dist-info/METADATA
scsims-3.0.6.dist-info/WHEEL
scsims-3.0.6.dist-info/top_level.txt
scsims-3.0.6.dist-info/RECORD
