Metadata-Version: 2.1
Name: scsims
Version: 3.0.6
Summary: Scalable, Interpretable Deep Learning for Single-Cell RNA-seq Classification
Home-page: https://github.com/braingeneers/sims
Author: Julian Lehrer
Author-email: jmlehrer@ucsc.edu
License: MIT license
Keywords: scsims
Platform: UNKNOWN
Classifier: Development Status :: 3 - Alpha
Classifier: Intended Audience :: Developers
Classifier: License :: OSI Approved :: GNU General Public License v2 (GPLv2)
Classifier: Natural Language :: English
Classifier: Programming Language :: Python :: 3
Classifier: Programming Language :: Python :: 3.6
Classifier: Programming Language :: Python :: 3.7
Classifier: Programming Language :: Python :: 3.8
Requires-Python: >=3.9
License-File: LICENSE
Requires-Dist: aiohttp (==3.8.4)
Requires-Dist: aiosignal (==1.3.1)
Requires-Dist: anndata (==0.9.1)
Requires-Dist: anyio (==3.6.2)
Requires-Dist: appdirs (==1.4.4)
Requires-Dist: arrow (==1.2.3)
Requires-Dist: async-timeout (==4.0.2)
Requires-Dist: attrs (==23.1.0)
Requires-Dist: beautifulsoup4 (==4.12.2)
Requires-Dist: blessed (==1.20.0)
Requires-Dist: boto3 (==1.26.130)
Requires-Dist: botocore (==1.29.130)
Requires-Dist: certifi (==2023.5.7)
Requires-Dist: charset-normalizer (==3.1.0)
Requires-Dist: click (==8.1.3)
Requires-Dist: contourpy (==1.0.7)
Requires-Dist: croniter (==1.3.14)
Requires-Dist: cycler (==0.11.0)
Requires-Dist: dateutils (==0.6.12)
Requires-Dist: deepdiff (==6.3.0)
Requires-Dist: docker-pycreds (==0.4.0)
Requires-Dist: fastapi (==0.88.0)
Requires-Dist: fonttools (==4.39.3)
Requires-Dist: fortran-language-server (==1.12.0)
Requires-Dist: frozenlist (==1.3.3)
Requires-Dist: fsspec (==2023.5.0)
Requires-Dist: gitdb (==4.0.10)
Requires-Dist: GitPython (==3.1.31)
Requires-Dist: h11 (==0.14.0)
Requires-Dist: h5py (==3.8.0)
Requires-Dist: idna (==3.4)
Requires-Dist: importlib-resources (==5.12.0)
Requires-Dist: inquirer (==3.1.3)
Requires-Dist: itsdangerous (==2.1.2)
Requires-Dist: Jinja2 (==3.1.2)
Requires-Dist: jmespath (==1.0.1)
Requires-Dist: joblib (==1.2.0)
Requires-Dist: kiwisolver (==1.4.4)
Requires-Dist: lightning (==2.0.2)
Requires-Dist: lightning-cloud (==0.5.34)
Requires-Dist: lightning-utilities (==0.8.0)
Requires-Dist: llvmlite (==0.40.0)
Requires-Dist: markdown-it-py (==2.2.0)
Requires-Dist: MarkupSafe (==2.1.2)
Requires-Dist: matplotlib (==3.7.1)
Requires-Dist: mdurl (==0.1.2)
Requires-Dist: multidict (==6.0.4)
Requires-Dist: natsort (==8.3.1)
Requires-Dist: networkx (==3.1)
Requires-Dist: numba (==0.57.0)
Requires-Dist: numpy (==1.24.3)
Requires-Dist: ordered-set (==4.1.0)
Requires-Dist: packaging (==23.1)
Requires-Dist: pandas (==2.0.1)
Requires-Dist: pathtools (==0.1.2)
Requires-Dist: patsy (==0.5.3)
Requires-Dist: Pillow (==9.5.0)
Requires-Dist: protobuf (==4.23.0)
Requires-Dist: psutil (==5.9.5)
Requires-Dist: pydantic (==1.10.7)
Requires-Dist: Pygments (==2.15.1)
Requires-Dist: PyJWT (==2.6.0)
Requires-Dist: pynndescent (==0.5.10)
Requires-Dist: pyparsing (==3.0.9)
Requires-Dist: python-dateutil (==2.8.2)
Requires-Dist: python-editor (==1.0.4)
Requires-Dist: python-multipart (==0.0.6)
Requires-Dist: pytorch-lightning (==2.0.2)
Requires-Dist: pytorch-tabnet (==4.0)
Requires-Dist: pytz (==2023.3)
Requires-Dist: PyYAML (==6.0)
Requires-Dist: readchar (==4.0.5)
Requires-Dist: requests (==2.30.0)
Requires-Dist: rich (==13.3.5)
Requires-Dist: s3transfer (==0.6.1)
Requires-Dist: scanpy (==1.9.3)
Requires-Dist: scikit-learn (==1.2.2)
Requires-Dist: scipy (==1.10.1)
Requires-Dist: seaborn (==0.12.2)
Requires-Dist: sentry-sdk (==1.22.2)
Requires-Dist: session-info (==1.0.0)
Requires-Dist: setproctitle (==1.3.2)
Requires-Dist: six (==1.16.0)
Requires-Dist: smmap (==5.0.0)
Requires-Dist: sniffio (==1.3.0)
Requires-Dist: soupsieve (==2.4.1)
Requires-Dist: starlette (==0.22.0)
Requires-Dist: starsessions (==1.3.0)
Requires-Dist: statsmodels (==0.14.0)
Requires-Dist: stdlib-list (==0.8.0)
Requires-Dist: threadpoolctl (==3.1.0)
Requires-Dist: torch (==1.13.1)
Requires-Dist: torchmetrics (==0.11.4)
Requires-Dist: tqdm (==4.65.0)
Requires-Dist: traitlets (==5.9.0)
Requires-Dist: typing-extensions (==4.5.0)
Requires-Dist: tzdata (==2023.3)
Requires-Dist: umap-learn (==0.5.3)
Requires-Dist: urllib3 (==1.26.15)
Requires-Dist: uvicorn (==0.22.0)
Requires-Dist: wandb (==0.15.2)
Requires-Dist: wcwidth (==0.2.6)
Requires-Dist: websocket-client (==1.5.1)
Requires-Dist: websockets (==11.0.3)
Requires-Dist: yarl (==1.9.2)
Requires-Dist: zipp (==3.15.0)
